[
  {
    "thread_title": "Čínský dron-launcher v civilním kamionu",
    "tweets": [
      {
        "number": 1,
        "content": "1/7 🚨 Čína krátce ukázala a pak rychle smazala záběry drona-launcheru schovaného v civilním nákladním voze. Co to znamená pro budoucnost válčení? Vlákno 🧵",
        "char_count": 154
      },
      {
        "number": 2,
        "content": "2/7 🔍 Zařízení vypadá jako běžný civilní kamion, ale ve skutečnosti nese odpalovací systém pro drony. Objevilo se ve státních médiích - a bylo rychle staženo. Náhoda? Sotva.",
        "char_count": 173
      },
      {
        "number": 3,
        "content": "3/7 📊 Proč je to zásadní: levná, obtížně odhalitelná úderná schopnost. Ideální pro státy i nestátní aktéry, kteří si nemohou dovolit klasické letectvo. Impact skóre 7/10.",
        "char_count": 170
      },
      {
        "number": 4,
        "content": "4/7 🌍 Toto by mohlo změnit asymetrickou válku od Blízkého východu po Afriku. Levné, mobilní, skryté zbraně dostupné i chudším aktérům = nová éra konfliktů.",
        "char_count": 155
      },
      {
        "number": 5,
        "content": "5/7 💡 Co si experti neuvědomují: smazání záběrů může být test mezinárodní reakce PŘED oficiálním spuštěním exportní doktríny. Připomíná to íránský playbook s drony.",
        "char_count": 164
      },
      {
        "number": 6,
        "content": "6/7 🎯 Co sledovat: potvrzená pozorování systému nebo poptávky od čínských zbrojních klientů v příštích týdnech. Rychlá reakce nepravděpodobná, ale vývoj sledujeme.",
        "char_count": 163
      },
      {
        "number": 7,
        "content": "7/7 ⚡ Pro Evropu a ČR to znamená nutnost sledovat proliferaci levných dron-systémů - hranice mezi konvenční a asymetrickou hrozbou se stírá. Co si o tom myslíte? #geopolitika #bezpečnost #drony",
        "char_count": 193
      }
    ],
    "hashtags": [
      "#geopolitika",
      "#bezpečnost",
      "#drony"
    ],
    "estimated_engagement": 7.8,
    "main_topic": "drony",
    "source_analysis_id": "China's Truck-Mounted Drone Launcher Signals New Export Model for Dispersed, Deniable Airpower",
    "generated_at": "2026-07-04T08:35:20.969341"
  }
]